odoo8_addon_web_m2x_options-8.0.0.2.0.99.dev38-py2.7-nspkg.pth
odoo8_addon_web_m2x_options-8.0.0.2.0.99.dev38.dist-info/METADATA
odoo8_addon_web_m2x_options-8.0.0.2.0.99.dev38.dist-info/RECORD
odoo8_addon_web_m2x_options-8.0.0.2.0.99.dev38.dist-info/WHEEL
odoo8_addon_web_m2x_options-8.0.0.2.0.99.dev38.dist-info/namespace_packages.txt
odoo8_addon_web_m2x_options-8.0.0.2.0.99.dev38.dist-info/top_level.txt
odoo_addons/web_m2x_options/README.rst
odoo_addons/web_m2x_options/__init__.py
odoo_addons/web_m2x_options/__openerp__.py
odoo_addons/web_m2x_options/i18n/ar.po
odoo_addons/web_m2x_options/i18n/ca.po
odoo_addons/web_m2x_options/i18n/de.po
odoo_addons/web_m2x_options/i18n/es.po
odoo_addons/web_m2x_options/i18n/es_ES.po
odoo_addons/web_m2x_options/i18n/eu.po
odoo_addons/web_m2x_options/i18n/fi.po
odoo_addons/web_m2x_options/i18n/fr.po
odoo_addons/web_m2x_options/i18n/hr.po
odoo_addons/web_m2x_options/i18n/hr_HR.po
odoo_addons/web_m2x_options/i18n/it.po
odoo_addons/web_m2x_options/i18n/nb_NO.po
odoo_addons/web_m2x_options/i18n/nl.po
odoo_addons/web_m2x_options/i18n/pt_BR.po
odoo_addons/web_m2x_options/i18n/sl.po
odoo_addons/web_m2x_options/i18n/tr.po
odoo_addons/web_m2x_options/i18n/tr_TR.po
odoo_addons/web_m2x_options/i18n/web_m2x_options.pot
odoo_addons/web_m2x_options/i18n/zh_CN.po
odoo_addons/web_m2x_options/models/__init__.py
odoo_addons/web_m2x_options/models/model.py
odoo_addons/web_m2x_options/static/description/icon.png
odoo_addons/web_m2x_options/static/description/index.html
odoo_addons/web_m2x_options/static/src/js/form.js
odoo_addons/web_m2x_options/static/src/xml/base.xml
odoo_addons/web_m2x_options/views/model_view.xml
odoo_addons/web_m2x_options/views/view.xml
