Metadata-Version: 2.1
Name: odoo8-addon-web-m2x-options
Version: 8.0.0.2.0.99.dev38
Summary: web_m2x_options
Home-page: UNKNOWN
Author: 0k.io,Odoo Community Association (OCA)
Author-email: support@odoo-community.org
License: AGPL-3
Platform: UNKNOWN
Classifier: Programming Language :: Python
Classifier: Framework :: Odoo
Classifier: License :: OSI Approved :: GNU Affero General Public License v3
Requires-Python: ~=2.7
Requires-Dist: odoo (<9.0a,>=8.0a)
